AndroidFridaManager/FridaManager.py
AndroidFridaManager/__init__.py
AndroidFridaManager/about.py
AndroidFridaManager/job.py
AndroidFridaManager/job_manager.py
androidfridamanager-1.9.4.dist-info/licenses/LICENSE
androidfridamanager-1.9.4.dist-info/METADATA
androidfridamanager-1.9.4.dist-info/WHEEL
androidfridamanager-1.9.4.dist-info/entry_points.txt
androidfridamanager-1.9.4.dist-info/top_level.txt
androidfridamanager-1.9.4.dist-info/RECORD
