Metadata-Version: 2.4
Name: AndroidFridaManager
Version: 1.9.4
Summary: A python API in order to install and run the frida-server on an Android device.
Home-page: https://github.com/fkie-cad/AndroidFridaManager
Author: Daniel Baier
Author-email: daniel.baier@fkie.fraunhofer.de
License: GPL v3
Keywords: mobile,instrumentation,frida,hook,android
Classifier: License :: OSI Approved :: GNU General Public License v3 (GPLv3)
Classifier: Operating System :: OS Independent
Classifier: Natural Language :: English
Classifier: Programming Language :: Python :: 3 :: Only
Classifier: Programming Language :: JavaScript
Classifier: Topic :: Security
Classifier: Topic :: Software Development :: Debuggers
Requires-Python: >=3.6
License-File: LICENSE
Requires-Dist: frida>=15.0.0
Requires-Dist: colorlog
Requires-Dist: requests
Dynamic: author
Dynamic: author-email
Dynamic: classifier
Dynamic: description
Dynamic: description-content-type
Dynamic: home-page
Dynamic: keywords
Dynamic: license
Dynamic: license-file
Dynamic: requires-dist
Dynamic: requires-python
Dynamic: summary
